{
  "quiz": [
    {
      "question_id": 1,
      "question": "Who wrote 'The Great Gatsby'?"
    },
    {
      "question_id": 2,
      "question": "Who wrote 'The Sound and the Fury'?"
    },
    {
      "question_id": 3,
      "question": "Who wrote 'Journey to the Center of the Earth'?"
    },
    {
      "question_id": 4,
      "question": "Who wrote 'Anna Karenina'?"
    },
    {
      "question_id": 5,
      "question": "Who wrote 'The Bell Jar'?"
    },
    {
      "question_id": 6,
      "question": "Who wrote 'The Secret Agent' about anarchism in London?"
    },
    {
      "question_id": 7,
      "question": "Who wrote 'Animal Farm'?"
    },
    {
      "question_id": 8,
      "question": "Who authored 'The Woman in White'?"
    },
    {
      "question_id": 9,
      "question": "Who wrote the modernist novel 'Mrs Dalloway'?"
    },
    {
      "question_id": 10,
      "question": "Who is the author of 'Crime and Punishment'?"
    },
    {
      "question_id": 11,
      "question": "Who is the author of 'The Stranger's' famous opening line in original language commonly attributed to?"
    },
    {
      "question_id": 12,
      "question": "Who wrote 'The Man Who Was Thursday' metaphysical thriller?"
    },
    {
      "question_id": 13,
      "question": "Who is the author of 'Les Misérables'?"
    },
    {
      "question_id": 14,
      "question": "Who is the author of 'The Metamorphosis'?"
    },
    {
      "question_id": 15,
      "question": "Who authored 'The Fixer' which won a Pulitzer in 1967?"
    }
  ]
}